pyworkflow/__init__.py
pyworkflow/config.py
pyworkflow/discovery.py
pyworkflow/aws/__init__.py
pyworkflow/aws/context.py
pyworkflow/aws/handler.py
pyworkflow/aws/testing.py
pyworkflow/celery/__init__.py
pyworkflow/celery/app.py
pyworkflow/celery/loop.py
pyworkflow/celery/scheduler.py
pyworkflow/celery/singleton.py
pyworkflow/celery/tasks.py
pyworkflow/cli/__init__.py
pyworkflow/cli/__main__.py
pyworkflow/cli/commands/__init__.py
pyworkflow/cli/commands/hooks.py
pyworkflow/cli/commands/quickstart.py
pyworkflow/cli/commands/runs.py
pyworkflow/cli/commands/scheduler.py
pyworkflow/cli/commands/schedules.py
pyworkflow/cli/commands/setup.py
pyworkflow/cli/commands/worker.py
pyworkflow/cli/commands/workflows.py
pyworkflow/cli/output/__init__.py
pyworkflow/cli/output/formatters.py
pyworkflow/cli/output/styles.py
pyworkflow/cli/utils/__init__.py
pyworkflow/cli/utils/async_helpers.py
pyworkflow/cli/utils/config.py
pyworkflow/cli/utils/config_generator.py
pyworkflow/cli/utils/discovery.py
pyworkflow/cli/utils/docker_manager.py
pyworkflow/cli/utils/interactive.py
pyworkflow/cli/utils/storage.py
pyworkflow/context/__init__.py
pyworkflow/context/aws.py
pyworkflow/context/base.py
pyworkflow/context/local.py
pyworkflow/context/mock.py
pyworkflow/context/step_context.py
pyworkflow/core/__init__.py
pyworkflow/core/exceptions.py
pyworkflow/core/registry.py
pyworkflow/core/scheduled.py
pyworkflow/core/step.py
pyworkflow/core/validation.py
pyworkflow/core/workflow.py
pyworkflow/engine/__init__.py
pyworkflow/engine/events.py
pyworkflow/engine/executor.py
pyworkflow/engine/replay.py
pyworkflow/observability/__init__.py
pyworkflow/observability/logging.py
pyworkflow/primitives/__init__.py
pyworkflow/primitives/child_handle.py
pyworkflow/primitives/child_workflow.py
pyworkflow/primitives/continue_as_new.py
pyworkflow/primitives/define_hook.py
pyworkflow/primitives/hooks.py
pyworkflow/primitives/resume_hook.py
pyworkflow/primitives/schedule.py
pyworkflow/primitives/shield.py
pyworkflow_engine-0.1.19.dist-info/licenses/LICENSE
pyworkflow_engine-0.1.19.dist-info/METADATA
pyworkflow_engine-0.1.19.dist-info/WHEEL
pyworkflow_engine-0.1.19.dist-info/entry_points.txt
pyworkflow_engine-0.1.19.dist-info/top_level.txt
pyworkflow_engine-0.1.19.dist-info/RECORD
