Metadata-Version: 2.4
Name: pyworkflow-engine
Version: 0.1.19
Summary: A Python implementation of durable, event-sourced workflows inspired by Vercel Workflow
Author: PyWorkflow Contributors
License: MIT
Project-URL: Homepage, https://docs.pyworkflow.dev
Project-URL: Documentation, https://docs.pyworkflow.dev
Project-URL: Repository, https://github.com/QualityUnit/pyworkflow
Project-URL: Issues, https://github.com/QualityUnit/pyworkflow/issues
Keywords: workflow,durable,event-sourcing,celery,async,orchestration
Classifier: Development Status :: 3 - Alpha
Classifier: Intended Audience :: Developers
Classifier: License :: OSI Approved :: MIT License
Classifier: Programming Language :: Python :: 3
Classifier: Programming Language :: Python :: 3.11
Classifier: Programming Language :: Python :: 3.12
Classifier: Programming Language :: Python :: 3.13
Classifier: Topic :: Software Development :: Libraries :: Python Modules
Classifier: Topic :: System :: Distributed Computing
Classifier: Framework :: Celery
Requires-Python: >=3.11
License-File: LICENSE
Requires-Dist: celery<6.0.0,>=5.3.0
Requires-Dist: cloudpickle>=3.0.0
Requires-Dist: pydantic<3.0.0,>=2.0.0
Requires-Dist: loguru>=0.7.0
Requires-Dist: click>=8.0.0
Requires-Dist: inquirerpy>=0.3.4; python_version < "4.0"
Requires-Dist: httpx>=0.25.0
Requires-Dist: python-dateutil>=2.8.0
Requires-Dist: filelock>=3.12.0
Requires-Dist: pyyaml>=6.0.0
Requires-Dist: croniter>=2.0.0
Provides-Extra: redis
Requires-Dist: redis>=5.0.0; extra == "redis"
Provides-Extra: sqlite
Requires-Dist: aiosqlite>=0.19.0; extra == "sqlite"
Provides-Extra: postgres
Requires-Dist: asyncpg>=0.29.0; extra == "postgres"
Provides-Extra: aws
Requires-Dist: aws-durable-execution-sdk-python>=0.1.0; extra == "aws"
Provides-Extra: dynamodb
Requires-Dist: aiobotocore>=2.5.0; extra == "dynamodb"
Provides-Extra: cassandra
Requires-Dist: cassandra-driver>=3.29.0; extra == "cassandra"
Provides-Extra: mysql
Requires-Dist: aiomysql>=0.2.0; extra == "mysql"
Provides-Extra: all
Requires-Dist: redis>=5.0.0; extra == "all"
Requires-Dist: aiosqlite>=0.19.0; extra == "all"
Requires-Dist: asyncpg>=0.29.0; extra == "all"
Requires-Dist: aiomysql>=0.2.0; extra == "all"
Requires-Dist: aws-durable-execution-sdk-python>=0.1.0; extra == "all"
Requires-Dist: cassandra-driver>=3.29.0; extra == "all"
Provides-Extra: dev
Requires-Dist: pytest>=7.4.0; extra == "dev"
Requires-Dist: pytest-asyncio>=0.21.0; extra == "dev"
Requires-Dist: pytest-cov>=4.1.0; extra == "dev"
Requires-Dist: pytest-celery>=0.0.0; extra == "dev"
Requires-Dist: pytest-mock>=3.12.0; extra == "dev"
Requires-Dist: moto[dynamodb]>=5.0.0; extra == "dev"
Requires-Dist: black>=23.0.0; extra == "dev"
Requires-Dist: ruff>=0.1.0; extra == "dev"
Requires-Dist: mypy>=1.7.0; extra == "dev"
Requires-Dist: pre-commit>=3.5.0; extra == "dev"
Requires-Dist: types-redis>=4.6.0; extra == "dev"
Requires-Dist: types-python-dateutil>=2.8.0; extra == "dev"
Requires-Dist: types-PyYAML>=6.0.0; extra == "dev"
Requires-Dist: flower>=2.0.0; extra == "dev"
Requires-Dist: redis>=5.0.0; extra == "dev"
Requires-Dist: aiosqlite>=0.19.0; extra == "dev"
Requires-Dist: asyncpg>=0.29.0; extra == "dev"
Dynamic: license-file
